Metadata-Version: 1.1
Name: suji
Version: 0.1.0
Summary: Japanese number notation converter
Home-page: https://github.com/jikyo/suji4p
Author: Junnosuke Moriya
Author-email: shinsen.jikyo@gmail.com
License: Apache License 2.0
Platform: UNKNOWN
Classifier: Development Status :: 4 - Beta
Classifier: Intended Audience :: Developers
Classifier: License :: OSI Approved :: Apache Software License
Classifier: Programming Language :: Python
Classifier: Programming Language :: Python :: 3
Classifier: Topic :: Software Development :: Libraries
Classifier: Natural Language :: Japanese
